{"account_id": "ACC-001", "amount_gbp": 500.0}
{"transaction_id": "TXN-1", "account_id": "ACC-002"}
{"transaction_id": "TXN-2", "amount_gbp": "NOT_A_NUMBER"}
{}
{"transaction_id": null, "amount_gbp": -999.0}
{"account_id": "ACC-001", "amount_gbp": 500.0}
{"transaction_id": "TXN-6", "account_id": "ACC-002"}
{"transaction_id": "TXN-7", "amount_gbp": "NOT_A_NUMBER"}
{}
{"transaction_id": null, "amount_gbp": -999.0}
{"account_id": "ACC-001", "amount_gbp": 500.0}
{"transaction_id": "TXN-11", "account_id": "ACC-002"}
{"transaction_id": "TXN-12", "amount_gbp": "NOT_A_NUMBER"}
{}
{"transaction_id": null, "amount_gbp": -999.0}
{"account_id": "ACC-001", "amount_gbp": 500.0}
{"transaction_id": "TXN-16", "account_id": "ACC-002"}
{"transaction_id": "TXN-17", "amount_gbp": "NOT_A_NUMBER"}
{}
{"transaction_id": null, "amount_gbp": -999.0}
